gntp/__init__.py
gntp/cli.py
gntp/config.py
gntp/core.py
gntp/errors.py
gntp/notifier.py
gntp/shim.py
gntp/version.py
gntp-1.0.2.dist-info/DESCRIPTION.rst
gntp-1.0.2.dist-info/entry_points.txt
gntp-1.0.2.dist-info/METADATA
gntp-1.0.2.dist-info/metadata.json
gntp-1.0.2.dist-info/RECORD
gntp-1.0.2.dist-info/top_level.txt
gntp-1.0.2.dist-info/WHEEL
